emsarray/__init__.py
emsarray/__main__.py
emsarray/accessors.py
emsarray/exceptions.py
emsarray/masking.py
emsarray/nco.py
emsarray/plot.py
emsarray/py.typed
emsarray/state.py
emsarray/transect.py
emsarray/tutorial.py
emsarray/types.py
emsarray/utils.py
emsarray/cli/__init__.py
emsarray/cli/command.py
emsarray/cli/exceptions.py
emsarray/cli/utils.py
emsarray/cli/commands/__init__.py
emsarray/cli/commands/clip.py
emsarray/cli/commands/export_geometry.py
emsarray/cli/commands/extract_points.py
emsarray/cli/commands/plot.py
emsarray/compat/__init__.py
emsarray/compat/shapely.py
emsarray/conventions/__init__.py
emsarray/conventions/_base.py
emsarray/conventions/_registry.py
emsarray/conventions/_utils.py
emsarray/conventions/arakawa_c.py
emsarray/conventions/grid.py
emsarray/conventions/shoc.py
emsarray/conventions/ugrid.py
emsarray/operations/__init__.py
emsarray/operations/cache.py
emsarray/operations/depth.py
emsarray/operations/geometry.py
emsarray/operations/point_extraction.py
emsarray/operations/triangulate.py
emsarray-0.10.0.dist-info/licenses/LICENSE
emsarray-0.10.0.dist-info/METADATA
emsarray-0.10.0.dist-info/WHEEL
emsarray-0.10.0.dist-info/entry_points.txt
emsarray-0.10.0.dist-info/top_level.txt
emsarray-0.10.0.dist-info/RECORD
