Metadata-Version: 2.4
Name: emsarray
Version: 0.10.0
Summary: xarray extension that supports multiple geometry conventions
Author-email: "Coastal Environmental Modelling team, Oceans and Atmosphere, CSIRO" <coasts@csiro.au>
License: Copyright 2023 Commonwealth Scientific and Industrial Research Organisation
Project-URL: Documentation, https://emsarray.readthedocs.io/
Project-URL: Release notes, https://emsarray.readthedocs.io/en/stable/releases/0.10.0/
Project-URL: Source, https://github.com/csiro-coasts/emsarray/
Requires-Python: >=3.11
License-File: LICENSE
Requires-Dist: bottleneck>=1.3
Requires-Dist: geojson>=3.1
Requires-Dist: netcdf4>=1.6.4
Requires-Dist: numpy>=1.25
Requires-Dist: packaging>=23.2
Requires-Dist: shapely>=2.0
Requires-Dist: pyshp>=2.3
Requires-Dist: xarray[parallel]>=2024.1
Provides-Extra: plot
Requires-Dist: cartopy>=0.22; extra == "plot"
Requires-Dist: matplotlib>=3.8; extra == "plot"
Requires-Dist: pykdtree>=1.3; extra == "plot"
Requires-Dist: cfunits>=3.3; extra == "plot"
Provides-Extra: tutorial
Requires-Dist: pooch>=1.8; extra == "tutorial"
Provides-Extra: complete
Requires-Dist: emsarray[plot,tutorial]; extra == "complete"
Provides-Extra: docs
Requires-Dist: emsarray[complete]; extra == "docs"
Requires-Dist: sphinx~=6.2.1; extra == "docs"
Requires-Dist: sphinx_book_theme~=1.0.1; extra == "docs"
Requires-Dist: livereload~=2.6.3; extra == "docs"
Provides-Extra: testing
Requires-Dist: emsarray[complete]; extra == "testing"
Requires-Dist: pytest; extra == "testing"
Requires-Dist: pytest-cov; extra == "testing"
Requires-Dist: pytest-mpl; extra == "testing"
Requires-Dist: mypy; extra == "testing"
Requires-Dist: pandas-stubs; extra == "testing"
Requires-Dist: types-pytz; extra == "testing"
Requires-Dist: flake8; extra == "testing"
Requires-Dist: isort; extra == "testing"
Requires-Dist: freezegun; extra == "testing"
Dynamic: license-file
